{
  "id": 2070976167,
  "loca_id": 18000,
  "faction": {
    "id": 2064723306,
    "loca_id": 1
  },
  "level": 43,
  "ship_type": 1,
  "is_scout": false,
  "is_outpost": false,
  "hull_type": 5,
  "rarity": 2,
  "strength": 75546101,
  "systems": [
    1702244411,
    814948003,
    1042011878
  ],
  "xp_amount": 1049,
  "warp": 75,
  "warp_with_superhighway": 75,
  "components": [
    {
      "id": 635429245,
      "art_id": 5001,
      "loca_id": 1,
      "build_cost": [],
      "repair_cost": [],
      "repair_time": -1,
      "scrap": [],
      "data": {
        "speed": 2,
        "distance": 2,
        "abilities": [],
        "tag": "Warp"
      },
      "order": -1,
      "build_time_in_seconds": 0
    },
    {
      "id": 3008741952,
      "art_id": 4001,
      "loca_id": 1,
      "build_cost": [],
      "repair_cost": [],
      "repair_time": -1,
      "scrap": [],
      "data": {
        "impulse": 15,
        "dodge": 355138,
        "tag": "Impulse"
      },
      "order": -1,
      "build_time_in_seconds": 0
    },
    {
      "id": 1290482993,
      "art_id": 3001,
      "loca_id": 1,
      "build_cost": [],
      "repair_cost": [],
      "repair_time": -1,
      "scrap": [],
      "data": {
        "absorption": 494793,
        "mitigation": 0.8,
        "hp": 53203446,
        "regen_time": 40,
        "tag": "Shield"
      },
      "order": -1,
      "build_time_in_seconds": 0
    },
    {
      "id": 2987071308,
      "art_id": 2001,
      "loca_id": 1,
      "build_cost": [],
      "repair_cost": [],
      "repair_time": -1,
      "scrap": [],
      "data": {
        "plating": 405873,
        "hp": 71886384,
        "tag": "Armor"
      },
      "order": -1,
      "build_time_in_seconds": 0
    },
    {
      "id": 2821665303,
      "art_id": 8000,
      "loca_id": 91002,
      "build_cost": [],
      "repair_cost": [],
      "repair_time": -1,
      "scrap": [],
      "data": {
        "tag": "Sensor"
      },
      "order": -1,
      "build_time_in_seconds": 0
    },
    {
      "id": 409142410,
      "art_id": 9000,
      "loca_id": 91003,
      "build_cost": [],
      "repair_cost": [],
      "repair_time": -1,
      "scrap": [],
      "data": {
        "deflection": 120,
        "tag": "Deflector"
      },
      "order": -1,
      "build_time_in_seconds": 0
    },
    {
      "id": 2534309121,
      "art_id": 6001,
      "loca_id": 1,
      "build_cost": [],
      "repair_cost": [],
      "repair_time": -1,
      "scrap": [],
      "data": {
        "max_resources": 0,
        "protected": 0,
        "tag": "Cargo"
      },
      "order": -1,
      "build_time_in_seconds": 0
    },
    {
      "id": 540814658,
      "art_id": 1001,
      "loca_id": 1,
      "build_cost": [],
      "repair_cost": [],
      "repair_time": -1,
      "scrap": [],
      "data": {
        "shots": 1,
        "warm_up": 1,
        "cool_down": 1,
        "accuracy": 216957,
        "penetration": 247952,
        "modulation": 289276,
        "minimum_damage": 528807,
        "maximum_damage": 646320,
        "crit_chance": 0.1,
        "crit_modifier": 1.5,
        "weapon_type": 1,
        "tag": "Weapon"
      },
      "order": 1,
      "build_time_in_seconds": 0
    },
    {
      "id": 540814658,
      "art_id": 1001,
      "loca_id": 1,
      "build_cost": [],
      "repair_cost": [],
      "repair_time": -1,
      "scrap": [],
      "data": {
        "shots": 1,
        "warm_up": 1,
        "cool_down": 1,
        "accuracy": 216957,
        "penetration": 247952,
        "modulation": 289276,
        "minimum_damage": 528807,
        "maximum_damage": 646320,
        "crit_chance": 0.1,
        "crit_modifier": 1.5,
        "weapon_type": 1,
        "tag": "Weapon"
      },
      "order": 1,
      "build_time_in_seconds": 0
    },
    {
      "id": 540814658,
      "art_id": 1001,
      "loca_id": 1,
      "build_cost": [],
      "repair_cost": [],
      "repair_time": -1,
      "scrap": [],
      "data": {
        "shots": 1,
        "warm_up": 1,
        "cool_down": 1,
        "accuracy": 216957,
        "penetration": 247952,
        "modulation": 289276,
        "minimum_damage": 528807,
        "maximum_damage": 646320,
        "crit_chance": 0.1,
        "crit_modifier": 1.5,
        "weapon_type": 1,
        "tag": "Weapon"
      },
      "order": 1,
      "build_time_in_seconds": 0
    },
    {
      "id": 2235181920,
      "art_id": 1501,
      "loca_id": 1,
      "build_cost": [],
      "repair_cost": [],
      "repair_time": -1,
      "scrap": [],
      "data": {
        "shots": 1,
        "warm_up": 1,
        "cool_down": 2,
        "accuracy": 216957,
        "penetration": 247952,
        "modulation": 289276,
        "minimum_damage": 1269139,
        "maximum_damage": 1551170,
        "crit_chance": 0.1,
        "crit_modifier": 1.5,
        "weapon_type": 2,
        "tag": "Weapon"
      },
      "order": 2,
      "build_time_in_seconds": 0
    },
    {
      "id": 2235181920,
      "art_id": 1501,
      "loca_id": 1,
      "build_cost": [],
      "repair_cost": [],
      "repair_time": -1,
      "scrap": [],
      "data": {
        "shots": 1,
        "warm_up": 1,
        "cool_down": 2,
        "accuracy": 216957,
        "penetration": 247952,
        "modulation": 289276,
        "minimum_damage": 1269139,
        "maximum_damage": 1551170,
        "crit_chance": 0.1,
        "crit_modifier": 1.5,
        "weapon_type": 2,
        "tag": "Weapon"
      },
      "order": 2,
      "build_time_in_seconds": 0
    },
    {
      "id": 2235181920,
      "art_id": 1501,
      "loca_id": 1,
      "build_cost": [],
      "repair_cost": [],
      "repair_time": -1,
      "scrap": [],
      "data": {
        "shots": 1,
        "warm_up": 1,
        "cool_down": 2,
        "accuracy": 216957,
        "penetration": 247952,
        "modulation": 289276,
        "minimum_damage": 1269139,
        "maximum_damage": 1551170,
        "crit_chance": 0.1,
        "crit_modifier": 1.5,
        "weapon_type": 2,
        "tag": "Weapon"
      },
      "order": 2,
      "build_time_in_seconds": 0
    }
  ],
  "resources": [
    {
      "resource_id": 2431852293,
      "min": 236000,
      "max": 278000
    },
    {
      "resource_id": 4135751670,
      "min": 25600,
      "max": 25600
    },
    {
      "resource_id": 156323681,
      "min": 12800,
      "max": 12800
    }
  ],
  "ability": [],
  "stats": {
    "health": 62544915,
    "defense": 6279020,
    "attack": 6722166,
    "dpr": 4459611,
    "strength": 75546101,
    "hull_hp": 71886384,
    "shield_hp": 53203446,
    "armor": 405873,
    "absorption": 494793,
    "dodge": 355138,
    "accuracy": 216957,
    "armor_piercing": 247952,
    "shield_piercing": 289276,
    "critical_chance": 0.09999999999999999,
    "critical_damage": 1.5
  }
}