{
  "id": 3807502347,
  "loca_id": 14019,
  "faction": {
    "id": 669838839,
    "loca_id": 3
  },
  "level": 47,
  "ship_type": 4,
  "is_scout": false,
  "is_outpost": false,
  "hull_type": 3,
  "rarity": 1,
  "strength": 16691638,
  "systems": [
    829165184,
    246615176,
    1072986698,
    1844514955,
    36276112,
    2119332338,
    1277114803,
    245752118,
    457323993,
    750762202,
    1128199135
  ],
  "xp_amount": 2786,
  "warp": 120,
  "warp_with_superhighway": 120,
  "components": [
    {
      "id": 635429245,
      "art_id": 5001,
      "loca_id": 1,
      "build_cost": [],
      "repair_cost": [],
      "repair_time": -1,
      "scrap": [],
      "data": {
        "speed": 2,
        "distance": 2,
        "abilities": [],
        "tag": "Warp"
      },
      "order": -1,
      "build_time_in_seconds": 0
    },
    {
      "id": 1415980884,
      "art_id": 4001,
      "loca_id": 1,
      "build_cost": [],
      "repair_cost": [],
      "repair_time": -1,
      "scrap": [],
      "data": {
        "impulse": 14,
        "dodge": 16303,
        "tag": "Impulse"
      },
      "order": -1,
      "build_time_in_seconds": 0
    },
    {
      "id": 389200370,
      "art_id": 3001,
      "loca_id": 1,
      "build_cost": [],
      "repair_cost": [],
      "repair_time": -1,
      "scrap": [],
      "data": {
        "absorption": 16303,
        "mitigation": 0.8,
        "hp": 7213675,
        "regen_time": 45,
        "tag": "Shield"
      },
      "order": -1,
      "build_time_in_seconds": 0
    },
    {
      "id": 2775831499,
      "art_id": 2001,
      "loca_id": 1,
      "build_cost": [],
      "repair_cost": [],
      "repair_time": -1,
      "scrap": [],
      "data": {
        "plating": 357418,
        "hp": 10580128,
        "tag": "Armor"
      },
      "order": -1,
      "build_time_in_seconds": 0
    },
    {
      "id": 2821665303,
      "art_id": 8000,
      "loca_id": 91002,
      "build_cost": [],
      "repair_cost": [],
      "repair_time": -1,
      "scrap": [],
      "data": {
        "tag": "Sensor"
      },
      "order": -1,
      "build_time_in_seconds": 0
    },
    {
      "id": 409142410,
      "art_id": 9000,
      "loca_id": 91003,
      "build_cost": [],
      "repair_cost": [],
      "repair_time": -1,
      "scrap": [],
      "data": {
        "deflection": 120,
        "tag": "Deflector"
      },
      "order": -1,
      "build_time_in_seconds": 0
    },
    {
      "id": 2534309121,
      "art_id": 6001,
      "loca_id": 1,
      "build_cost": [],
      "repair_cost": [],
      "repair_time": -1,
      "scrap": [],
      "data": {
        "max_resources": 0,
        "protected": 0,
        "tag": "Cargo"
      },
      "order": -1,
      "build_time_in_seconds": 0
    },
    {
      "id": 54076711,
      "art_id": 1001,
      "loca_id": 1,
      "build_cost": [],
      "repair_cost": [],
      "repair_time": -1,
      "scrap": [],
      "data": {
        "shots": 3,
        "warm_up": 1,
        "cool_down": 1,
        "accuracy": 200626,
        "penetration": 200626,
        "modulation": 357418,
        "minimum_damage": 374389,
        "maximum_damage": 457592,
        "crit_chance": 0.1,
        "crit_modifier": 1.8,
        "weapon_type": 1,
        "tag": "Weapon"
      },
      "order": -1,
      "build_time_in_seconds": 0
    },
    {
      "id": 54076711,
      "art_id": 1001,
      "loca_id": 1,
      "build_cost": [],
      "repair_cost": [],
      "repair_time": -1,
      "scrap": [],
      "data": {
        "shots": 3,
        "warm_up": 1,
        "cool_down": 1,
        "accuracy": 200626,
        "penetration": 200626,
        "modulation": 357418,
        "minimum_damage": 374389,
        "maximum_damage": 457592,
        "crit_chance": 0.1,
        "crit_modifier": 1.8,
        "weapon_type": 1,
        "tag": "Weapon"
      },
      "order": -1,
      "build_time_in_seconds": 0
    },
    {
      "id": 2735307809,
      "art_id": 1501,
      "loca_id": 1,
      "build_cost": [],
      "repair_cost": [],
      "repair_time": -1,
      "scrap": [],
      "data": {
        "shots": 3,
        "warm_up": 1,
        "cool_down": 2,
        "accuracy": 200626,
        "penetration": 200626,
        "modulation": 357418,
        "minimum_damage": 895623,
        "maximum_damage": 1094658,
        "crit_chance": 0.1,
        "crit_modifier": 1.8,
        "weapon_type": 2,
        "tag": "Weapon"
      },
      "order": -1,
      "build_time_in_seconds": 0
    }
  ],
  "resources": [
    {
      "resource_id": 3852104441,
      "min": 516,
      "max": 632
    },
    {
      "resource_id": 970475396,
      "min": 1600,
      "max": 1600
    },
    {
      "resource_id": 4135751670,
      "min": -6000,
      "max": -6000
    },
    {
      "resource_id": 156323681,
      "min": 3200,
      "max": 3200
    }
  ],
  "ability": [],
  "stats": {
    "health": 8896902,
    "defense": 1950120,
    "attack": 5844616,
    "dpr": 4706611,
    "strength": 16691638,
    "hull_hp": 10580128,
    "shield_hp": 7213675,
    "armor": 357418,
    "absorption": 16303,
    "dodge": 16303,
    "accuracy": 200626,
    "armor_piercing": 200626,
    "shield_piercing": 357418,
    "critical_chance": 0.10000000000000002,
    "critical_damage": 1.8
  }
}