{
  "id": 423352621,
  "loca_id": 10009,
  "faction": {
    "id": -1,
    "loca_id": null
  },
  "level": 13,
  "ship_type": 7,
  "is_scout": false,
  "is_outpost": false,
  "hull_type": 2,
  "rarity": 1,
  "strength": 3760,
  "systems": [
    81603,
    1490914183,
    1339989224,
    81641,
    81642,
    42,
    659054346,
    729358569,
    1910889934,
    2119979509,
    601072182,
    83351,
    83353,
    81085
  ],
  "xp_amount": 99,
  "warp": 5,
  "warp_with_superhighway": 5,
  "components": [
    {
      "id": 635429245,
      "art_id": 5001,
      "loca_id": 1,
      "build_cost": [],
      "repair_cost": [],
      "repair_time": -1,
      "scrap": [],
      "data": {
        "speed": 2,
        "distance": 2,
        "abilities": [],
        "tag": "Warp"
      },
      "order": -1,
      "build_time_in_seconds": 0
    },
    {
      "id": 415968277,
      "art_id": 4001,
      "loca_id": 1,
      "build_cost": [],
      "repair_cost": [],
      "repair_time": -1,
      "scrap": [],
      "data": {
        "impulse": 14,
        "dodge": 55,
        "tag": "Impulse"
      },
      "order": -1,
      "build_time_in_seconds": 0
    },
    {
      "id": 758110328,
      "art_id": 3001,
      "loca_id": 1,
      "build_cost": [],
      "repair_cost": [],
      "repair_time": -1,
      "scrap": [],
      "data": {
        "absorption": 219,
        "mitigation": 0.8,
        "hp": 680,
        "regen_time": 30,
        "tag": "Shield"
      },
      "order": -1,
      "build_time_in_seconds": 0
    },
    {
      "id": 1319145652,
      "art_id": 2001,
      "loca_id": 1,
      "build_cost": [],
      "repair_cost": [],
      "repair_time": -1,
      "scrap": [],
      "data": {
        "plating": 55,
        "hp": 650,
        "tag": "Armor"
      },
      "order": -1,
      "build_time_in_seconds": 0
    },
    {
      "id": 2821665303,
      "art_id": 8000,
      "loca_id": 91002,
      "build_cost": [],
      "repair_cost": [],
      "repair_time": -1,
      "scrap": [],
      "data": {
        "tag": "Sensor"
      },
      "order": -1,
      "build_time_in_seconds": 0
    },
    {
      "id": 409142410,
      "art_id": 9000,
      "loca_id": 91003,
      "build_cost": [],
      "repair_cost": [],
      "repair_time": -1,
      "scrap": [],
      "data": {
        "deflection": 120,
        "tag": "Deflector"
      },
      "order": -1,
      "build_time_in_seconds": 0
    },
    {
      "id": 2534309121,
      "art_id": 6001,
      "loca_id": 1,
      "build_cost": [],
      "repair_cost": [],
      "repair_time": -1,
      "scrap": [],
      "data": {
        "max_resources": 0,
        "protected": 0,
        "tag": "Cargo"
      },
      "order": -1,
      "build_time_in_seconds": 0
    },
    {
      "id": 3000108805,
      "art_id": 1001,
      "loca_id": 1,
      "build_cost": [],
      "repair_cost": [],
      "repair_time": -1,
      "scrap": [],
      "data": {
        "shots": 1,
        "warm_up": 1,
        "cool_down": 1,
        "accuracy": 328,
        "penetration": 55,
        "modulation": 55,
        "minimum_damage": 396,
        "maximum_damage": 484,
        "crit_chance": 0.1,
        "crit_modifier": 1.5,
        "weapon_type": 1,
        "tag": "Weapon"
      },
      "order": -1,
      "build_time_in_seconds": 0
    },
    {
      "id": 3000108805,
      "art_id": 1001,
      "loca_id": 1,
      "build_cost": [],
      "repair_cost": [],
      "repair_time": -1,
      "scrap": [],
      "data": {
        "shots": 1,
        "warm_up": 1,
        "cool_down": 1,
        "accuracy": 328,
        "penetration": 55,
        "modulation": 55,
        "minimum_damage": 396,
        "maximum_damage": 484,
        "crit_chance": 0.1,
        "crit_modifier": 1.5,
        "weapon_type": 1,
        "tag": "Weapon"
      },
      "order": -1,
      "build_time_in_seconds": 0
    }
  ],
  "resources": [
    {
      "resource_id": 743985951,
      "min": 103,
      "max": 140
    }
  ],
  "ability": [],
  "stats": {
    "health": 665,
    "defense": 1645,
    "attack": 1450,
    "dpr": 1012,
    "strength": 3760,
    "hull_hp": 650,
    "shield_hp": 680,
    "armor": 55,
    "absorption": 219,
    "dodge": 55,
    "accuracy": 328,
    "armor_piercing": 55,
    "shield_piercing": 55,
    "critical_chance": 0.1,
    "critical_damage": 1.5
  }
}