{
  "id": 835389708,
  "loca_id": 85507,
  "faction": {
    "id": 4269128921,
    "loca_id": 84002
  },
  "level": 64,
  "ship_type": 5,
  "is_scout": false,
  "is_outpost": false,
  "hull_type": 0,
  "rarity": 1,
  "strength": 217499832066,
  "systems": [
    984494800,
    1846507791,
    366289310
  ],
  "xp_amount": 0,
  "warp": 900,
  "warp_with_superhighway": 900,
  "components": [
    {
      "id": 635429245,
      "art_id": 5001,
      "loca_id": 1,
      "build_cost": [],
      "repair_cost": [],
      "repair_time": -1,
      "scrap": [],
      "data": {
        "speed": 2,
        "distance": 2,
        "abilities": [],
        "tag": "Warp"
      },
      "order": -1,
      "build_time_in_seconds": 0
    },
    {
      "id": 180841422,
      "art_id": 4001,
      "loca_id": 1,
      "build_cost": [],
      "repair_cost": [],
      "repair_time": -1,
      "scrap": [],
      "data": {
        "impulse": 80,
        "dodge": 137122373,
        "tag": "Impulse"
      },
      "order": -1,
      "build_time_in_seconds": 0
    },
    {
      "id": 2204407136,
      "art_id": 3001,
      "loca_id": 1,
      "build_cost": [],
      "repair_cost": [],
      "repair_time": -1,
      "scrap": [],
      "data": {
        "absorption": 4971890,
        "mitigation": 0.8,
        "hp": 77567883971,
        "regen_time": 40,
        "tag": "Shield"
      },
      "order": -1,
      "build_time_in_seconds": 0
    },
    {
      "id": 3952917418,
      "art_id": 2001,
      "loca_id": 1,
      "build_cost": [],
      "repair_cost": [],
      "repair_time": -1,
      "scrap": [],
      "data": {
        "plating": 9943779,
        "hp": 310271535883,
        "tag": "Armor"
      },
      "order": -1,
      "build_time_in_seconds": 0
    },
    {
      "id": 2821665303,
      "art_id": 8000,
      "loca_id": 91002,
      "build_cost": [],
      "repair_cost": [],
      "repair_time": -1,
      "scrap": [],
      "data": {
        "tag": "Sensor"
      },
      "order": -1,
      "build_time_in_seconds": 0
    },
    {
      "id": 409142410,
      "art_id": 9000,
      "loca_id": 91003,
      "build_cost": [],
      "repair_cost": [],
      "repair_time": -1,
      "scrap": [],
      "data": {
        "deflection": 120,
        "tag": "Deflector"
      },
      "order": -1,
      "build_time_in_seconds": 0
    },
    {
      "id": 2534309121,
      "art_id": 6001,
      "loca_id": 1,
      "build_cost": [],
      "repair_cost": [],
      "repair_time": -1,
      "scrap": [],
      "data": {
        "max_resources": 0,
        "protected": 0,
        "tag": "Cargo"
      },
      "order": -1,
      "build_time_in_seconds": 0
    },
    {
      "id": 4113355139,
      "art_id": 1001,
      "loca_id": 1,
      "build_cost": [],
      "repair_cost": [],
      "repair_time": -1,
      "scrap": [],
      "data": {
        "shots": 2,
        "warm_up": 1,
        "cool_down": 1,
        "accuracy": 15910046,
        "penetration": 39775116,
        "modulation": 7955023,
        "minimum_damage": 2840558956,
        "maximum_damage": 3087564083,
        "crit_chance": 0.1,
        "crit_modifier": 1.5,
        "weapon_type": 1,
        "tag": "Weapon"
      },
      "order": -1,
      "build_time_in_seconds": 0
    },
    {
      "id": 2986828427,
      "art_id": 1501,
      "loca_id": 1,
      "build_cost": [],
      "repair_cost": [],
      "repair_time": -1,
      "scrap": [],
      "data": {
        "shots": 1,
        "warm_up": 1,
        "cool_down": 1,
        "accuracy": 15910046,
        "penetration": 39775116,
        "modulation": 7955023,
        "minimum_damage": 7574823885,
        "maximum_damage": 8233504223,
        "crit_chance": 0.1,
        "crit_modifier": 1.5,
        "weapon_type": 2,
        "tag": "Weapon"
      },
      "order": -1,
      "build_time_in_seconds": 0
    },
    {
      "id": 4113355139,
      "art_id": 1001,
      "loca_id": 1,
      "build_cost": [],
      "repair_cost": [],
      "repair_time": -1,
      "scrap": [],
      "data": {
        "shots": 2,
        "warm_up": 1,
        "cool_down": 1,
        "accuracy": 15910046,
        "penetration": 39775116,
        "modulation": 7955023,
        "minimum_damage": 2840558956,
        "maximum_damage": 3087564083,
        "crit_chance": 0.1,
        "crit_modifier": 1.5,
        "weapon_type": 1,
        "tag": "Weapon"
      },
      "order": -1,
      "build_time_in_seconds": 0
    }
  ],
  "resources": [
    {
      "resource_id": 252423364,
      "min": 45,
      "max": 45
    },
    {
      "resource_id": 931309915,
      "min": 200,
      "max": 200
    },
    {
      "resource_id": 2575628328,
      "min": 60,
      "max": 60
    },
    {
      "resource_id": 2115116650,
      "min": 20,
      "max": 20
    }
  ],
  "ability": [
    {
      "id": 56799195,
      "value_is_percentage": true,
      "values": [
        {
          "value": 0.08,
          "chance": 1
        },
        {
          "value": 0.08,
          "chance": 1
        },
        {
          "value": 0.08,
          "chance": 1
        },
        {
          "value": 0.08,
          "chance": 1
        },
        {
          "value": 0.08,
          "chance": 1
        },
        {
          "value": 0.08,
          "chance": 1
        },
        {
          "value": 0.08,
          "chance": 1
        },
        {
          "value": 0.08,
          "chance": 1
        },
        {
          "value": 0.08,
          "chance": 1
        },
        {
          "value": 0.08,
          "chance": 1
        },
        {
          "value": 0.08,
          "chance": 1
        },
        {
          "value": 0.08,
          "chance": 1
        },
        {
          "value": 0.08,
          "chance": 1
        },
        {
          "value": 0.08,
          "chance": 1
        },
        {
          "value": 0.08,
          "chance": 1
        },
        {
          "value": 0.08,
          "chance": 1
        },
        {
          "value": 0.08,
          "chance": 1
        },
        {
          "value": 0.08,
          "chance": 1
        },
        {
          "value": 0.08,
          "chance": 1
        },
        {
          "value": 0.08,
          "chance": 1
        },
        {
          "value": 0.08,
          "chance": 1
        },
        {
          "value": 0.08,
          "chance": 1
        },
        {
          "value": 0.08,
          "chance": 1
        },
        {
          "value": 0.08,
          "chance": 1
        },
        {
          "value": 0.08,
          "chance": 1
        },
        {
          "value": 0.08,
          "chance": 1
        },
        {
          "value": 0.08,
          "chance": 1
        },
        {
          "value": 0.08,
          "chance": 1
        },
        {
          "value": 0.08,
          "chance": 1
        },
        {
          "value": 0.08,
          "chance": 1
        },
        {
          "value": 0.08,
          "chance": 1
        },
        {
          "value": 0.08,
          "chance": 1
        },
        {
          "value": 0.08,
          "chance": 1
        },
        {
          "value": 0.08,
          "chance": 1
        },
        {
          "value": 0.08,
          "chance": 1
        },
        {
          "value": 0.08,
          "chance": 1
        },
        {
          "value": 0.08,
          "chance": 1
        },
        {
          "value": 0.08,
          "chance": 1
        },
        {
          "value": 0.08,
          "chance": 1
        },
        {
          "value": 0.08,
          "chance": 1
        },
        {
          "value": 0.08,
          "chance": 1
        },
        {
          "value": 0.08,
          "chance": 1
        },
        {
          "value": 0.08,
          "chance": 1
        },
        {
          "value": 0.08,
          "chance": 1
        },
        {
          "value": 0.08,
          "chance": 1
        },
        {
          "value": 0.08,
          "chance": 1
        },
        {
          "value": 0.08,
          "chance": 1
        },
        {
          "value": 0.08,
          "chance": 1
        },
        {
          "value": 0.08,
          "chance": 1
        },
        {
          "value": 0.08,
          "chance": 1
        },
        {
          "value": 0.08,
          "chance": 1
        },
        {
          "value": 0.08,
          "chance": 1
        },
        {
          "value": 0.08,
          "chance": 1
        },
        {
          "value": 0.08,
          "chance": 1
        },
        {
          "value": 0.08,
          "chance": 1
        },
        {
          "value": 0.08,
          "chance": 1
        },
        {
          "value": 0.08,
          "chance": 1
        },
        {
          "value": 0.08,
          "chance": 1
        },
        {
          "value": 0.08,
          "chance": 1
        },
        {
          "value": 0.08,
          "chance": 1
        },
        {
          "value": 0.08,
          "chance": 1
        },
        {
          "value": 0.08,
          "chance": 1
        },
        {
          "value": 0.08,
          "chance": 1
        },
        {
          "value": 0.08,
          "chance": 1
        },
        {
          "value": 0.08,
          "chance": 1
        },
        {
          "value": 0.08,
          "chance": 1
        },
        {
          "value": 0.08,
          "chance": 1
        },
        {
          "value": 0.08,
          "chance": 1
        },
        {
          "value": 0.08,
          "chance": 1
        },
        {
          "value": 0.08,
          "chance": 1
        },
        {
          "value": 0.08,
          "chance": 1
        },
        {
          "value": 0.08,
          "chance": 1
        },
        {
          "value": 0.08,
          "chance": 1
        },
        {
          "value": 0.08,
          "chance": 1
        },
        {
          "value": 0.08,
          "chance": 1
        },
        {
          "value": 0.08,
          "chance": 1
        },
        {
          "value": 0.08,
          "chance": 1
        },
        {
          "value": 0.08,
          "chance": 1
        },
        {
          "value": 0.08,
          "chance": 1
        },
        {
          "value": 0.08,
          "chance": 1
        },
        {
          "value": 0.08,
          "chance": 1
        },
        {
          "value": 0.08,
          "chance": 1
        },
        {
          "value": 0.08,
          "chance": 1
        },
        {
          "value": 0.08,
          "chance": 1
        },
        {
          "value": 0.08,
          "chance": 1
        },
        {
          "value": 0.08,
          "chance": 1
        },
        {
          "value": 0.08,
          "chance": 1
        },
        {
          "value": 0.08,
          "chance": 1
        },
        {
          "value": 0.08,
          "chance": 1
        },
        {
          "value": 0.08,
          "chance": 1
        }
      ],
      "art_id": 492,
      "loca_id": 84505,
      "show_percentage": true,
      "value_type": true
    },
    {
      "id": 2486538514,
      "value_is_percentage": false,
      "values": [
        {
          "value": 1.5,
          "chance": 1
        },
        {
          "value": 1.5,
          "chance": 1
        },
        {
          "value": 1.5,
          "chance": 1
        },
        {
          "value": 1.5,
          "chance": 1
        },
        {
          "value": 1.5,
          "chance": 1
        },
        {
          "value": 1.5,
          "chance": 1
        },
        {
          "value": 1.5,
          "chance": 1
        },
        {
          "value": 1.5,
          "chance": 1
        },
        {
          "value": 1.5,
          "chance": 1
        },
        {
          "value": 1.5,
          "chance": 1
        },
        {
          "value": 1.5,
          "chance": 1
        },
        {
          "value": 1.5,
          "chance": 1
        },
        {
          "value": 1.5,
          "chance": 1
        },
        {
          "value": 1.5,
          "chance": 1
        },
        {
          "value": 1.5,
          "chance": 1
        },
        {
          "value": 1.5,
          "chance": 1
        },
        {
          "value": 1.5,
          "chance": 1
        },
        {
          "value": 1.5,
          "chance": 1
        },
        {
          "value": 1.5,
          "chance": 1
        },
        {
          "value": 1.5,
          "chance": 1
        },
        {
          "value": 1.5,
          "chance": 1
        },
        {
          "value": 1.5,
          "chance": 1
        },
        {
          "value": 1.5,
          "chance": 1
        },
        {
          "value": 1.5,
          "chance": 1
        },
        {
          "value": 1.5,
          "chance": 1
        },
        {
          "value": 1.5,
          "chance": 1
        },
        {
          "value": 1.5,
          "chance": 1
        },
        {
          "value": 1.5,
          "chance": 1
        },
        {
          "value": 1.5,
          "chance": 1
        },
        {
          "value": 1.5,
          "chance": 1
        },
        {
          "value": 1.5,
          "chance": 1
        },
        {
          "value": 1.5,
          "chance": 1
        },
        {
          "value": 1.5,
          "chance": 1
        },
        {
          "value": 1.5,
          "chance": 1
        },
        {
          "value": 1.5,
          "chance": 1
        },
        {
          "value": 1.5,
          "chance": 1
        },
        {
          "value": 1.5,
          "chance": 1
        },
        {
          "value": 1.5,
          "chance": 1
        },
        {
          "value": 1.5,
          "chance": 1
        },
        {
          "value": 1.5,
          "chance": 1
        },
        {
          "value": 1.5,
          "chance": 1
        },
        {
          "value": 1.5,
          "chance": 1
        },
        {
          "value": 1.5,
          "chance": 1
        },
        {
          "value": 1.5,
          "chance": 1
        },
        {
          "value": 1.5,
          "chance": 1
        },
        {
          "value": 1.5,
          "chance": 1
        },
        {
          "value": 1.5,
          "chance": 1
        },
        {
          "value": 1.5,
          "chance": 1
        },
        {
          "value": 1.5,
          "chance": 1
        },
        {
          "value": 1.5,
          "chance": 1
        },
        {
          "value": 1.5,
          "chance": 1
        },
        {
          "value": 1.5,
          "chance": 1
        },
        {
          "value": 1.5,
          "chance": 1
        },
        {
          "value": 1.5,
          "chance": 1
        },
        {
          "value": 1.5,
          "chance": 1
        },
        {
          "value": 1.5,
          "chance": 1
        },
        {
          "value": 1.5,
          "chance": 1
        },
        {
          "value": 1.5,
          "chance": 1
        },
        {
          "value": 1.5,
          "chance": 1
        },
        {
          "value": 1.5,
          "chance": 1
        },
        {
          "value": 1.5,
          "chance": 1
        },
        {
          "value": 1.5,
          "chance": 1
        },
        {
          "value": 1.5,
          "chance": 1
        },
        {
          "value": 1.5,
          "chance": 1
        },
        {
          "value": 1.5,
          "chance": 1
        },
        {
          "value": 1.5,
          "chance": 1
        },
        {
          "value": 1.5,
          "chance": 1
        },
        {
          "value": 1.5,
          "chance": 1
        },
        {
          "value": 1.5,
          "chance": 1
        },
        {
          "value": 1.5,
          "chance": 1
        },
        {
          "value": 1.5,
          "chance": 1
        },
        {
          "value": 1.5,
          "chance": 1
        },
        {
          "value": 1.5,
          "chance": 1
        },
        {
          "value": 1.5,
          "chance": 1
        },
        {
          "value": 1.5,
          "chance": 1
        },
        {
          "value": 1.5,
          "chance": 1
        },
        {
          "value": 1.5,
          "chance": 1
        },
        {
          "value": 1.5,
          "chance": 1
        },
        {
          "value": 1.5,
          "chance": 1
        },
        {
          "value": 1.5,
          "chance": 1
        },
        {
          "value": 1.5,
          "chance": 1
        },
        {
          "value": 1.5,
          "chance": 1
        },
        {
          "value": 1.5,
          "chance": 1
        },
        {
          "value": 1.5,
          "chance": 1
        },
        {
          "value": 1.5,
          "chance": 1
        },
        {
          "value": 1.5,
          "chance": 1
        },
        {
          "value": 1.5,
          "chance": 1
        },
        {
          "value": 1.5,
          "chance": 1
        },
        {
          "value": 1.5,
          "chance": 1
        },
        {
          "value": 1.5,
          "chance": 1
        }
      ],
      "art_id": 505,
      "loca_id": 84507,
      "show_percentage": true,
      "value_type": true
    }
  ],
  "stats": {
    "health": 193919709927,
    "defense": 760190210,
    "attack": 22819931929,
    "dpr": 22724471652,
    "strength": 217499832066,
    "hull_hp": 310271535883,
    "shield_hp": 77567883971,
    "armor": 9943779,
    "absorption": 4971890,
    "dodge": 137122373,
    "accuracy": 15910046,
    "armor_piercing": 39775116,
    "shield_piercing": 7955023,
    "critical_chance": 0.10000000000000002,
    "critical_damage": 1.5
  }
}